{
	"ItemClasses": [
		{
			"ItemClass": "Class01",
			"DisplayName": "Class01",
			"isSelectable": true,
			"isUsable": true,
			"isGiveable": true,
			"isDroppable": true,
			"isAutoDroppable": false,
			"isPickable": true,
			"isAutoPickable": true,
			"isConsumable": false,
			"mass": 1.0,
			"dropImpulse": 1.0,
			"shouldRemoveOnDrop": false,
			"isUsableUnderWater": false,
			"isWeapon": false,
			"isUniqueInventory": true,
			"isUniqueEquipment": true,
			"isAmmo": false,
			"annimationTag": "",
			"isAttachedToBack": false
		},
		{
			"ItemClass": "Class02",
			"DisplayName": "Class02",
			"isSelectable": true,
			"isUsable": true,
			"isGiveable": true,
			"isDroppable": true,
			"isAutoDroppable": false,
			"isPickable": true,
			"isAutoPickable": true,
			"isConsumable": false,
			"mass": 1.0,
			"dropImpulse": 1.0,
			"shouldRemoveOnDrop": false,
			"isUsableUnderWater": false,
			"isWeapon": false,
			"isUniqueInventory": true,
			"isUniqueEquipment": true,
			"isAmmo": false,
			"annimationTag": "",
			"isAttachedToBack": false
		},
		{
			"ItemClass": "Keycard",
			"DisplayName": "Keycard",
			"isSelectable": true,
			"isUsable": true,
			"isGiveable": true,
			"isDroppable": true,
			"isAutoDroppable": false,
			"isPickable": true,
			"isAutoPickable": true,
			"isConsumable": false,
			"mass": 1.0,
			"dropImpulse": 1.0,
			"shouldRemoveOnDrop": false,
			"isUsableUnderWater": false,
			"isWeapon": false,
			"isUniqueInventory": true,
			"isUniqueEquipment": true,
			"isAmmo": false,
			"annimationTag": "",
			"isAttachedToBack": false
		}
	]
}